tms_integration/__init__.py
tms_integration/carlo/__init__.py
tms_integration/carlo/carlo.py
tms_integration/carlo/models/__init__.py
tms_integration/carlo/models/order.py
tms_integration/lis_winsped/__init__.py
tms_integration/lis_winsped/lis_winsped.py
tms_integration/lis_winsped/models/__init__.py
tms_integration/lis_winsped/models/lisin.py
tms_integration/lis_winsped/models/lisout.py
tms_integration/lis_winsped/models/types/__init__.py
tms_integration/lis_winsped/models/types/adr.py
tms_integration/lis_winsped/models/types/auftrag.py
tms_integration/lis_winsped/models/types/custom.py
tms_integration/lis_winsped/models/types/dmsdok.py
tms_integration/lis_winsped/models/types/dmsref.py
tms_integration/lis_winsped/models/types/dmssw.py
tms_integration/lis_winsped/models/types/ende.py
tms_integration/lis_winsped/models/types/geb.py
tms_integration/lis_winsped/models/types/ggut.py
tms_integration/lis_winsped/models/types/ladeli.py
tms_integration/lis_winsped/models/types/lademi.py
tms_integration/lis_winsped/models/types/posit.py
tms_integration/lis_winsped/models/types/start.py
tms_integration/lis_winsped/models/types/status.py
tms_integration/lis_winsped/models/types/text.py
tms_integration/utils/__init__.py
tms_integration/utils/xml.py
tms_integration/utils/sftp/__init__.py
tms_integration/utils/sftp/base.py
tms_integration-0.2.0.dist-info/licenses/LICENSE
tms_integration-0.2.0.dist-info/METADATA
tms_integration-0.2.0.dist-info/WHEEL
tms_integration-0.2.0.dist-info/top_level.txt
tms_integration-0.2.0.dist-info/RECORD
