Metadata-Version: 2.4
Name: tms_integration
Version: 0.2.0
Summary: A library for TMS integration
Home-page: https://github.com/F-ONE-Group/tms_integration/tree/pypi
Author: F-ONE Group
Author-email: admin@f-one.group
Classifier: Programming Language :: Python :: 3
Classifier: License :: OSI Approved :: MIT License
Classifier: Operating System :: OS Independent
Requires-Python: >=3.6
License-File: LICENSE
Requires-Dist: pydantic<3.0,>2.0.0
Requires-Dist: pytz
Provides-Extra: lis-winsped
Requires-Dist: pysftp==0.2.9; extra == "lis-winsped"
Requires-Dist: paramiko==3.5.1; extra == "lis-winsped"
Provides-Extra: carlo
Requires-Dist: pysftp==0.2.9; extra == "carlo"
Dynamic: author
Dynamic: author-email
Dynamic: classifier
Dynamic: description
Dynamic: description-content-type
Dynamic: home-page
Dynamic: license-file
Dynamic: provides-extra
Dynamic: requires-dist
Dynamic: requires-python
Dynamic: summary
